setup.py
stock/__init__.py
stock/main.py
stock_info.egg-info/PKG-INFO
stock_info.egg-info/SOURCES.txt
stock_info.egg-info/dependency_links.txt
stock_info.egg-info/entry_points.txt
stock_info.egg-info/requires.txt
stock_info.egg-info/top_level.txt