Metadata-Version: 1.0
Name: stock-info
Version: 1.0.0
Summary: show the price of the stock
Home-page: https://github.com/zhenchaozhu/stock_info
Author: zhenchaozhu
Author-email: zhenchaozhu@outlook.com
License: UNKNOWN
Platform: UNKNOWN
